aicmo/__init__.py
aicmo-0.0.3.dist-info/METADATA
aicmo-0.0.3.dist-info/WHEEL
aicmo-0.0.3.dist-info/top_level.txt
aicmo-0.0.3.dist-info/RECORD
