Metadata-Version: 2.4
Name: aicmo
Version: 0.0.3
Summary: A package for using aicmo functions and tools
Author: Jayr Castro
Author-email: jayrcastro.py@gmail.com
Keywords: aicmo
Classifier: Development Status :: 4 - Beta
Classifier: Intended Audience :: Developers
Classifier: Programming Language :: Python :: 3.12
Classifier: Operating System :: Unix
Classifier: Operating System :: MacOS :: MacOS X
Classifier: Operating System :: Microsoft :: Windows
Requires-Dist: openai==1.75.0
Requires-Dist: scrapingbee==2.0.1
Requires-Dist: requests==2.32.3
Requires-Dist: boto3==1.37.37
Requires-Dist: tiktoken==0.9.0
Requires-Dist: opencv-python-headless==4.11.0.86
Requires-Dist: beautifulsoup4==4.13.4
Requires-Dist: numpy==2.2.4
Requires-Dist: python-dotenv==1.1.0
Requires-Dist: typesense==1.0.3
Dynamic: author
Dynamic: author-email
Dynamic: classifier
Dynamic: description
Dynamic: description-content-type
Dynamic: keywords
Dynamic: requires-dist
Dynamic: summary
